ml_versioning_tools-2.0.1.data/scripts/check_all_scripts_consistency
ml_versioning_tools-2.0.1.data/scripts/check_script_consistency
ml_versioning_tools-2.0.1.data/scripts/export_pipeline
ml_versioning_tools-2.0.1.data/scripts/gen_dvc
ml_versioning_tools-2.0.1.data/scripts/ipynb_to_dvc
ml_versioning_tools-2.0.1.data/scripts/ipynb_to_python
mlvtools/__init__.py
mlvtools/check_script.py
mlvtools/cmd.py
mlvtools/exception.py
mlvtools/export_pipeline.py
mlvtools/gen_dvc.py
mlvtools/helper.py
mlvtools/ipynb_to_dvc.py
mlvtools/ipynb_to_python.py
mlvtools/conf/__init__.py
mlvtools/conf/conf.py
mlvtools/diff/__init__.py
mlvtools/diff/parse.py
mlvtools/docstring_helpers/__init__.py
mlvtools/docstring_helpers/extract.py
mlvtools/docstring_helpers/parse.py
mlvtools/mlv_dvc/__init__.py
mlvtools/mlv_dvc/dvc_parser.py
mlvtools/templates/dvc-cmd.tpl
mlvtools/templates/ml-python.tpl
mlvtools/templates/pipeline-export.tpl
ml_versioning_tools-2.0.1.dist-info/LICENSE
ml_versioning_tools-2.0.1.dist-info/METADATA
ml_versioning_tools-2.0.1.dist-info/WHEEL
ml_versioning_tools-2.0.1.dist-info/top_level.txt
ml_versioning_tools-2.0.1.dist-info/RECORD
