Metadata-Version: 2.1
Name: ml-versioning-tools
Version: 2.0.1
Summary: Set of Machine Learning versioning helpers
Home-page: http://github.com/peopledoc/ml-versionning-tools
Author: PeopleDoc
Author-email: pdoc-team-ml@ultimatesoftware.com
License: UNKNOWN
Keywords: peopledoc,machine learning,versioning,mlvtools
Platform: UNKNOWN
Classifier: Programming Language :: Python :: 3
Requires-Dist: docstring-parser (>=0.3)
Requires-Dist: Jinja2 (>=2.10.1)
Requires-Dist: nbconvert
Requires-Dist: pydantic (>=1.0)
Requires-Dist: PyYAML
Requires-Dist: networkx
Requires-Dist: yapf
Provides-Extra: dev
Requires-Dist: pytest ; extra == 'dev'
Requires-Dist: flake8 ; extra == 'dev'
Requires-Dist: pytest-cov ; extra == 'dev'
Requires-Dist: pytest-mock ; extra == 'dev'
Requires-Dist: twine ; extra == 'dev'
Requires-Dist: dvc ; extra == 'dev'
